odoo/addons/ssi_partner_identification_cpa_license/README.rst
odoo/addons/ssi_partner_identification_cpa_license/__init__.py
odoo/addons/ssi_partner_identification_cpa_license/__manifest__.py
odoo/addons/ssi_partner_identification_cpa_license/data/res_partner_id_category_data.xml
odoo/addons/ssi_partner_identification_cpa_license/models/__init__.py
odoo/addons/ssi_partner_identification_cpa_license/models/res_partner.py
odoo/addons/ssi_partner_identification_cpa_license/static/description/icon.png
odoo14_addon_ssi_partner_identification_cpa_license-14.0.1.0.1.dist-info/METADATA
odoo14_addon_ssi_partner_identification_cpa_license-14.0.1.0.1.dist-info/WHEEL
odoo14_addon_ssi_partner_identification_cpa_license-14.0.1.0.1.dist-info/top_level.txt
odoo14_addon_ssi_partner_identification_cpa_license-14.0.1.0.1.dist-info/RECORD
